{"developers_bnb-smart-chain.md":"Q7SBXusG","developers_canto.md":"H1UlMVgH","developers_extension-bitcoin.md":"OU3YxQXd","developers_extension-evms.md":"f_tRoipg","developers_extension-litecoin.md":"XbeGGnIn","developers_extension-cosmos.md":"qIgGfEGY","developers_extension-detect-xdefi-providers.md":"qIaM_Dec","developers_extension-dogecoin.md":"I5QbBcjO","developers_extension-solana.md":"6xe12G33","developers_extension-terra.md":"YWoHi80j","developers_extension-thorchain.md":"yR1MBzpE","developers_extension-near.md":"KXpY4oAm","developers_extension-wallet.md":"HgKA1vvC","developers_fantom.md":"yNXcPtOF","developers_introduction.md":"VHwKTarl","developers_klaytn.md":"h6nVoP58","developers_libraries-integration.md":"efuoBgMx","developers_litecoin.md":"85dbtF6n","developers_gnosis.md":"cWnfpmwP","developers_maya.md":"yKfyFJoN","developers_mobile-dogecoin.md":"WiqIlQ8Z","developers_mobile-ethereum.md":"RFbZy3RX","developers_mobile-litecoin.md":"AzVB-00u","developers_mobile-near.md":"GPyA2Cxp","developers_mobile-optimism.md":"r3refhHl","developers_mobile-bitcoin-cash.md":"zLzJKYJr","developers_mobile-bitcoin.md":"b9YSuYsB","developers_mobile-cosmos.md":"tstXtDjM","developers_mobile-binance.md":"z7yQaE_l","developers_mobile-terra.md":"RsCV7YDh","developers_mobile-testnets.md":"DWA3icrV","developers_mobile-solana.md":"1XyaVZde","developers_mobile-thorchain.md":"kbw7xLGT","developers_mobile-wallet.md":"vV4VZa_A","developers_mobile-zetachain.md":"3X6ELrWp","developers_solana-adapter-xdefi-integration.md":"tNWRH_Po","developers_solana.md":"PtJie96L","developers_terra.md":"H3k62rXh","developers_thorchain.md":"BrY5M4yv","index.md":"6tSv1ExI","developers_xdefi-wallet-integration.md":"bgvTZ-AH","developers_polygon.md":"u6BeqgC9","developers_optimism.md":"QRy6ssIR","developers_rainbowkit-xdefi-integration.md":"Let7L8EV","developers_near.md":"4AalubBH","routing_endpoints.md":"XmSA_IiS","routing_introduction.md":"XWXUf7J5","routing_query-mutation-details.md":"IRHdkj09","routing_routing-graph-ql-api.md":"Is5k38Rs","routing_snipet.md":"hisWZO2D","routing_widget-integration.md":"AJuJabDe","developers_bitcoin-cash.md":"ipzm9ruy","developers_blocknative-xdefi-integration.md":"S5PeGeJA","developers_cosmos.md":"5MJqtQRX","developers_blockchains-integration.md":"Frxl4G71","readme.md":"iE8mlZfE","developers_cosmoskit-xdefi-integration.md":"1slvGFZA","developers_bnb-beacon-chain.md":"ozVYfgRH","routing_swap-example.md":"rfZe-YfI","developers_aurora.md":"-jyZ9bAk","developers_avalanche.md":"SVzeg4tI","about_xdefi-technologies_bug-bounty-program.md":"yvZ2kcSA","developers_bitcoin.md":"92qi86bX","about_xdefi-technologies_mobile-wallet.md":"5St1yUhV","about_xdefi-technologies_native-integration.md":"IPBghf_K","about_xdefi-technologies_supported-blockchains.md":"P3QzDr0L","about_xdefi-technologies_supported-nfts.md":"JsU2ASxC","about_xdefi-token_buy-xdefi.md":"rUWjl4JK","about_xdefi-token_revenue.md":"XjqTuvzx","about_xdefi.md":"ELmJsb1z","developers_arbitrum.md":"1kKNyLwF","developers_ethereum.md":"fOmaAec0","about_xdefi-technologies_faq.md":"9A9H8tMH","about_xdefi-technologies_routing-api.md":"n14rqVoK","about_xdefi-technologies_supported-hardware-wallets.md":"S2AP4kyx","developers_cronos.md":"zaARTN3P","about_xdefi-token_utility.md":"tfP7bBo3","about_xdefi-technologies_custom-integration.md":"RHXnddhz","about_xdefi-technologies_how-to-add-custom-network.md":"tQnBLbL8","developers_dogecoin.md":"o12mjw3q","campaigns_campaigns-service-api.md":"psVF2bzR","about_xdefi-token_introduction.md":"b3q81q0T","about_xdefi-technologies_extension-wallet.md":"hiwI_b2B","about_xdefi-technologies_web-app.md":"1QDSHCgN","about_xdefi-technologies_audits.md":"kblBJBXy","about_xdefi-technologies_introduction.md":"qWdLBpro","about_xdefi-token_tokenomics.md":"w5kAfNXn","about_xdefi-token_staking.md":"zJAKD8dY","developers_extension-binance.md":"tcAViZt1","developers_extension-bitcoin-cash.md":"4ofvfIUZ","developers_mobile-polygon.md":"rgE6lmsM"}
