{"contributing.md":"U-a2L9GE","about_xdefi-technologies_bug-bounty-program.md":"NSD0wSsN","about_xdefi-technologies_change-custom-rpc.md":"zaQKfudU","about_xdefi-technologies_custom-integration.md":"uTAw3MbH","readme.md":"H3oB7yhi","about_xdefi-technologies_supported-blockchains.md":"SZxg35jS","about_xdefi-token_introduction.md":"KgSOFzs5","about_xdefi-token_staking.md":"6zNhOQjR","about_xdefi-token_revenue.md":"_zpQxGcD","about_xdefi-technologies_introduction.md":"0XINfUKH","about_xdefi-technologies_mobile-wallet.md":"v6IUmpfD","about_xdefi-technologies_audits.md":"K_ZYQkop","about_xdefi-technologies_extension-wallet.md":"GjitFyTs","about_xdefi-technologies_web-app.md":"oR_yOiXB","about_xdefi-technologies_supported-hardware-wallets.md":"3KiqTBIE","about_xdefi-technologies_add-custom-network.md":"Ip1R-QEO","about_xdefi-technologies_routing-api.md":"fX4qVrOX","about_xdefi-technologies_supported-nfts.md":"EYiQKckO","about_xdefi-technologies_native-integration.md":"E4KpW7vM","about_xdefi-technologies_faq.md":"mZqRw7Sr","about_xdefi.md":"HWfd_19X","about_xdefi-token_buy-xdefi.md":"j9-T0O99","about_xdefi-token_tokenomics.md":"BWGUZnjY","about_xdefi-token_utility.md":"V9BcF_Ld","developers_kava.md":"XYr_DXXg","developers_blockchains-integration.md":"6lixe4vB","developers_avalanche.md":"QTJc3ujh","developers__xfi.md":"NSEe2NuX","developers_juno.md":"SAXMdeJK","developers_bitcoin-cash.md":"fg1CCblX","developers_extension-bitcoin-cash.md":"LKH13QK3","developers__evm.md":"g_hhPU1T","developers_mobile-dogecoin.md":"xnPq1eAc","developers_mobile-bitcoin-cash.md":"p7wxaomf","developers_mobile-ethereum.md":"25-Pg2jv","index.md":"ClctGSD7","gas-tank_messages-service.md":"I0axoEQC","developers_maya.md":"4vE3nY-A","developers_mobile-solana.md":"ZDnUvUI0","developers_cosmoskit-xdefi-integration.md":"Jd39ggqT","developers_mobile-testnets.md":"__OxCZM-","developers_bitcoin.md":"fZo9SPFt","developers_mobile-thorchain.md":"QR6IALBc","gas-tank_other-services.md":"CFf0MQcL","developers_mobile-wallet.md":"bml6VSon","routing_endpoints.md":"z0NrgEBK","chains-lib_chains-lib.md":"giLS60H_","routing_introduction.md":"U847F0ic","developers_mobile-zetachain.md":"Cul4WGbN","developers_axelar.md":"wgYw89Cr","developers_extension-litecoin.md":"bCjPQiP8","developers_mobile-cosmos.md":"CYkIr3m-","developers_canto.md":"CVhGRRBN","developers_near.md":"bgq3Ivcc","developers_mobile-bitcoin.md":"-tS8qrXR","developers_ethereum.md":"NkJi8YsT","developers_aurora.md":"USS9mC-_","developers_other-blockchains.md":"aTD1HRjg","developers_extension-binance.md":"U2gr7iVg","developers_extension-cosmos.md":"7Qd5KWod","developers_extension-dogecoin.md":"alL6sXt7","developers_mars.md":"AqkGJVgf","developers_cronos.md":"OTenzxjw","developers_extension-near.md":"g1GP3ptJ","developers_libraries-integration.md":"Ssb6KBFx","developers_extension-terra.md":"qu9y-Pvo","campaigns_campaigns-service-api.md":"jFsWei7C","developers_polygon.md":"Y1O04JUc","developers_extension-bitcoin.md":"vQO3HlXZ","developers_osmosis.md":"VlYAcYZD","developers_bnb-smart-chain.md":"uq9Mxsmr","developers_akash.md":"mNx9kSW-","developers_terra.md":"h-sh2ERq","developers_thorchain.md":"o1gLBM7C","developers_mobile-polygon.md":"hndeal0-","routing_routing-graph-ql-api.md":"sQHsYSa9","gas-tank_authentication-services.md":"h1tDduBa","developers_xdefi-wallet-integration.md":"Il7YELE6","developers_litecoin.md":"B4A62zWH","developers_solana.md":"AmJom1oh","developers_extension-detect-xdefi-providers.md":"TZfX85Vv","gas-tank_balance-services.md":"KmZxJAyJ","developers_kujira.md":"ycdXjk_Q","gas-tank_chains-services.md":"peVrPR0o","developers_arbitrum.md":"QE8797PZ","developers_bnb-beacon-chain.md":"aO7DIU15","developers_extension-evms.md":"PWpKmCal","developers_mobile-optimism.md":"lXi06BTh","developers_crescent.md":"jxbSdB8S","developers_extension-wallet.md":"vr10JGvN","developers_dogecoin.md":"iNatvPj-","developers_mobile-terra.md":"BNgaUCUk","swap-widget_widget-integration.md":"fGhzwfeM","developers_optimism.md":"3C81m-Dl","developers_blocknative-xdefi-integration.md":"D0-2JKy8","developers_mobile-near.md":"ytVuXcch","developers_crypto-org.md":"To_mVTZ-","developers_mobile-binance.md":"Gh_xnlnO","developers__cosmos.md":"qsgurQ5b","developers_extension-thorchain.md":"BryWPGi6","developers_gnosis.md":"ADAiv_O_","staking_staking-api.md":"SgC6Wwc2","developers_rainbowkit-xdefi-integration.md":"ZMsrIPiu","developers_introduction.md":"exDFOMAs","developers_sei.md":"sRaVg_rt","gas-tank_gas-tank-api.md":"x3abPKHv","routing_swap-example.md":"G41C3zuK","developers_solana-adapter-xdefi-integration.md":"74gKxzsF","developers_stride.md":"bahNjtZc","developers_extension-solana.md":"sbKSrqss","developers_cosmos.md":"cfn5sDXz","developers_mobile-litecoin.md":"FG7NJ0qx","routing_snipet.md":"ZanI9VN5","indexers_indexers-api.md":"lTm5H2Gz","developers_stargaze.md":"25pJp4fm","developers_fantom.md":"n4GsAmLt","routing_query-mutation-details.md":"NVpR41FK","assets-services_assets-and-prices-api.md":"Z2KjxBAv"}
