{"about_xdefi-technologies_add-custom-network.md":"wjM2HwCc","about_xdefi-technologies_mobile-wallet.md":"8DpX-WPu","about_xdefi-technologies_native-integration.md":"iTID2-AJ","about_xdefi-technologies_bug-bounty-program.md":"Y7jYdDII","about_xdefi-technologies_supported-nfts.md":"JzidGCKP","about_xdefi-technologies_faq.md":"r_WLjl8h","readme.md":"N1230A6W","about_xdefi-technologies_custom-integration.md":"daqg-oTI","about_xdefi-token_introduction.md":"vo-8jnk6","contributing.md":"XF5Zv6o6","about_xdefi-technologies_audits.md":"sMt6AfV8","about_xdefi-technologies_web-app.md":"rYsuHfxv","about_xdefi-technologies_change-custom-rpc.md":"GDTnvytE","about_xdefi-token_buy-xdefi.md":"4twNVdqT","about_xdefi-technologies_routing-api.md":"rj8DSgOF","about_xdefi-token_staking.md":"x1CosZ5F","about_xdefi-token_revenue.md":"kSU3reyB","about_xdefi-technologies_supported-blockchains.md":"rT3fE752","about_xdefi-token_tokenomics.md":"U7ALRQmG","about_xdefi-token_utility.md":"h4fvc0rQ","about_xdefi.md":"5rOlHVCa","campaigns_campaigns-service-api.md":"XRCynfRB","about_xdefi-technologies_supported-hardware-wallets.md":"bJWvE2XW","about_xdefi-technologies_extension-wallet.md":"RipMCLQH","about_xdefi-technologies_introduction.md":"-Auk73tS","chains-lib_chains-lib.md":"IHmxcjjl","developers__xfi.md":"KQ9P8CoX","developers_aurora.md":"WLlVNZV8","developers_axelar.md":"X4iKq8T9","developers_blockchains-integration.md":"ikb1KcUv","developers_bitcoin.md":"OnhLZ6Kq","developers__cosmos.md":"h6FcW3Xo","developers_akash.md":"iVCVpjWC","developers_arbitrum.md":"x-xgljzG","developers_extension-solana.md":"UBefdFXQ","developers_extension-dogecoin.md":"l14K5Hoc","developers_extension-evms.md":"ZzAcFnpO","developers_extension-litecoin.md":"ChybBWxT","developers_extension-near.md":"5jHV5o6L","developers__evm.md":"qIJV3AkW","developers_extension-thorchain.md":"4FJzrAbl","developers_extension-terra.md":"NH90S_Wj","developers_extension-tron.md":"rVyQasMF","developers_extension-wallet.md":"vwCaZAVA","developers_mobile-cosmos.md":"fxvObFeS","developers_maya.md":"mTwMSz10","developers_mobile-binance.md":"tBmEyfTn","developers_mobile-bitcoin-cash.md":"5GhtcCnZ","developers_mobile-bitcoin.md":"50mQ4JD5","developers_canto.md":"C8feQZXb","developers_crescent.md":"bny1sgHf","developers_dogecoin.md":"pGec9cuO","developers_ethereum.md":"6HabWC_C","developers_mobile-dogecoin.md":"-7dLWkIK","routing_routing-graph-ql-api.md":"jvFPCDzq","developers_juno.md":"io-neT-d","developers_mars.md":"0kV249aG","developers_avalanche.md":"GLypVplg","developers_mobile-optimism.md":"MwZ6UNGc","developers_mobile-near.md":"6JSEoQlU","developers_solana-adapter-xdefi-integration.md":"N3n1WC1c","developers_solana.md":"riPGMgQx","developers_stride.md":"WY5JPSYA","developers_terra.md":"C5_RyHQ0","developers_cronos.md":"DPcp-VAH","routing_snipet.md":"vTaZvTjA","developers_kujira.md":"x1yINmV1","developers_mobile-tron.md":"A9AoLLu_","developers_mobile-polygon.md":"_zE0p5on","developers_mobile-solana.md":"u8IXFZqD","developers_mobile-terra.md":"IQljTH7Z","developers_mobile-testnets.md":"LJ0o2AxP","developers_mobile-thorchain.md":"eZZKgRA4","developers_blocknative-xdefi-integration.md":"70yD8MB5","developers_near.md":"v67MJ45S","developers_mobile-wallet.md":"Yot0s3Zz","developers_mobile-zetachain.md":"dcBpBbtd","swap-widget_widget-integration.md":"Zdz97lYi","developers_fantom.md":"TNDgXp3f","developers_optimism.md":"K0jpvWWK","developers_osmosis.md":"w8FHqhNp","developers_extension-detect-xdefi-providers.md":"mh-ByHFd","developers_mobile-litecoin.md":"8nz9_peG","developers_crypto-org.md":"5fbD-3GY","developers_mobile-ethereum.md":"NW5PgQ1p","developers_sei.md":"hsUJk3k6","developers_stargaze.md":"HU8mQtxT","gas-tank_authentication-services.md":"bugrnftz","developers_extension-binance.md":"4pmoB2Jz","developers_tron.md":"21l50RPX","developers_thorchain.md":"P1tb30qZ","gas-tank_chains-services.md":"-UX1_Jbn","developers_bnb-beacon-chain.md":"d9j0cGkc","assets-services_assets-and-prices-api.md":"Sg_x_ggi","developers_cosmoskit-xdefi-integration.md":"_08XVDFx","gas-tank_balance-services.md":"lRU-4G3X","developers_introduction.md":"8Ma-ZdrE","developers_ctrl-wallet-integration.md":"3RF9jfUw","developers_extension-bitcoin-cash.md":"BzjeisJe","developers_bnb-smart-chain.md":"KikFP6iy","developers_bitcoin-cash.md":"QxRE2ExR","developers_extension-bitcoin.md":"EWVkrZuJ","developers_gnosis.md":"gYnNVAli","gas-tank_other-services.md":"wLKOTS4L","developers_libraries-integration.md":"lUYIieHL","developers_litecoin.md":"bxQqV3za","developers_other-blockchains.md":"68ufihav","developers_kava.md":"77YZLR7A","routing_endpoints.md":"J8j7b3X-","developers_polygon.md":"e7IKxMMo","developers_extension-cosmos.md":"4LUfS7SW","developers_cosmos.md":"HZh-d6On","gas-tank_messages-service.md":"pWuqLjzt","routing_swap-example.md":"nZedrjaz","indexers_indexers-api.md":"Ia2R8Mh0","gas-tank_gas-tank-api.md":"aW21n9he","index.md":"dSNx2vtG","routing_introduction.md":"cwaKQpyO","developers_rainbowkit-xdefi-integration.md":"j86e36-a","staking_staking-api.md":"VsH8InrB","routing_query-mutation-details.md":"Wl6QrfKL"}
