{"about_xdefi-technologies_custom-integration.md":"5K8hD489","about_xdefi-technologies_extension-wallet.md":"t5vE_fxq","about_xdefi-technologies_web-app.md":"n1-2tsNB","about_xdefi-token_tokenomics.md":"MSFEqTBs","about_xdefi-technologies_change-custom-rpc.md":"6ZDCmLFq","about_xdefi-token_introduction.md":"BqjQpivq","about_xdefi-token_staking.md":"XAWy6LpV","about_xdefi-token_revenue.md":"mVB--ZGp","about_xdefi-technologies_routing-api.md":"osg_FMFM","about_xdefi-technologies_supported-hardware-wallets.md":"dOmkbKNz","readme.md":"RzHs8AcM","about_xdefi-technologies_supported-nfts.md":"yX39gF41","about_xdefi-technologies_add-custom-network.md":"v9N8oZE3","about_xdefi-technologies_audits.md":"KfpNyjzU","about_xdefi.md":"hcND1H2r","about_xdefi-technologies_supported-blockchains.md":"ok-bkql1","about_xdefi-technologies_mobile-wallet.md":"qJ0G6nb3","contributing.md":"z7sg3rUr","about_xdefi-technologies_native-integration.md":"s0nGUAZT","about_xdefi-technologies_introduction.md":"KhYTUZhq","developers_mars.md":"ZxpxGBrT","about_xdefi-technologies_bug-bounty-program.md":"UXnzRVyZ","about_xdefi-token_utility.md":"-IfqBlSR","about_xdefi-token_buy-xdefi.md":"v1W4tdxc","campaigns_campaigns-service-api.md":"zHED1MNu","developers_introduction.md":"k_Hxw0ec","developers__cosmos.md":"fB7OjGmC","developers_gnosis.md":"L6zD7gCQ","developers__evm.md":"Wrxrjj-u","developers__xfi.md":"ZWuVL7KF","developers_extension-bitcoin.md":"Bp3hxet-","developers_extension-cardano.md":"P-bAgVCx","developers_extension-cosmos.md":"5rLAompu","developers_extension-detect-xdefi-providers.md":"Heov3D8o","developers_extension-dogecoin.md":"79kXuYge","developers_akash.md":"1OZ2mgv2","developers_mobile-cosmos.md":"7G8OlUBI","developers_bnb-smart-chain.md":"5dJjFZT6","developers_extension-near.md":"Hwf8Gtyh","developers_extension-solana.md":"UpjGSpBr","developers_extension-terra.md":"ghf9iena","gas-tank_other-services.md":"SHwevCML","developers_near.md":"zW1llf2f","routing_routing-graph-ql-api.md":"pi_QMyle","routing_swap-example.md":"WIv3hIZK","developers_polygon.md":"QH6plMbm","developers_extension-bitcoin-cash.md":"fd024jC2","developers_kava.md":"-W9PzCnD","routing_query-mutation-details.md":"z-qJ67_B","developers_extension-litecoin.md":"IN7jqp4r","developers_sei.md":"2A3tk2ze","developers_thorchain.md":"DhlDQ6m7","developers_ctrl-wallet-integration.md":"BLcu76-v","developers_tron.md":"acCoHWvq","developers_solana.md":"wouZ564N","developers_stargaze.md":"JAqFZjIv","developers_solana-adapter-xdefi-integration.md":"NZiftHxH","developers_avalanche.md":"_n5VuZJj","developers_mobile-cardano.md":"XjqP4T-9","developers_mobile-litecoin.md":"PzfXJBSo","developers_mobile-tron.md":"VAc8DQVj","developers_osmosis.md":"PKDK076K","developers_libraries-integration.md":"pJws5uQW","developers_cosmos.md":"6egm9R_o","developers_axelar.md":"GhWL5m7q","developers_rainbowkit-xdefi-integration.md":"jy0N9srx","gas-tank_authentication-services.md":"XtlKUBBW","gas-tank_gas-tank-platform.md":"jZI224Lo","developers_mobile-dogecoin.md":"V0BmgMP5","developers_extension-thorchain.md":"g7-Vb_0r","developers_optimism.md":"o4wHX5jR","developers_extension-wallet.md":"UdWQA2xW","developers_blocknative-xdefi-integration.md":"MaFVvRs-","developers_mobile-solana.md":"9Nirt5yL","developers_extension-tron.md":"pvxCIJyw","index.md":"-mUuexe8","developers_canto.md":"YdvmhnRg","routing_snipet.md":"R98LxzIx","developers_bitcoin.md":"cC-Rj10c","developers_extension-evms.md":"1AY0uWOs","about_xdefi-technologies_faq.md":"-1XeXI20","developers_dogecoin.md":"tcgU6CsP","swap-widget_widget-integration.md":"_OHLIN-Y","gas-tank_balance-services.md":"fCbBCvgC","developers_stride.md":"jR8HfLma","developers_extension-binance.md":"iEbk-GD8","gas-tank_chains-services.md":"te-zs6Iy","developers_arbitrum.md":"OU3kvBPK","routing_introduction.md":"JeuklENW","gas-tank_messages-service.md":"gbz4WkUg","developers_kujira.md":"y1kDARR2","chains-lib_chains-lib.md":"PU38UONJ","developers_cosmoskit-xdefi-integration.md":"mS0uR9D6","gas-tank_gas-fee.md":"JfZ4Vla0","developers_maya.md":"LSZW8zrW","developers_litecoin.md":"Au0rg6nD","gas-tank_gas-tank-api.md":"xFPZ8QWs","indexers_indexers-api.md":"mjXhVdyv","developers_fantom.md":"FlumJoER","developers_bnb-beacon-chain.md":"PSltdjWx","routing_endpoints.md":"yBahnTzy","developers_mobile-bitcoin.md":"ZPe0EgTT","developers_bitcoin-cash.md":"sYZeqttj","developers_terra.md":"1MdqzKsF","developers_cronos.md":"8V2xddwF","developers_crescent.md":"nYVXsTdA","developers_ethereum.md":"HsSx71om","developers_crypto-org.md":"raw6m7rv","developers_mobile-wallet.md":"Ivi2EeFM","developers_mobile-ethereum.md":"iQIAbtA6","developers_other-blockchains.md":"sxumSdni","developers_juno.md":"_cTN_JqT","developers_blockchains-integration.md":"OYZrNsSD","developers_aurora.md":"Uv3RUubt","staking_staking-api.md":"lFtpz88t","assets-services_assets-and-prices-api.md":"K62yPItH"}
